{
	"key" : "enemy_gst07_SPECTER",
	"subfolder" : "level07",
	"name" : "SPECTER",
	"description" : "MED",
	"gender" : "NONE",
	"race" : "MONSTER",
	"family" : "mfamily_gst",
	"species" : "SPECTER",
	"appearance" : "4dir_ghost",
	"portrait" : "battle_portraits/gst.png",
	"meatEatLevel" : 8,
	"meatTargetLevel" : 7,
	"gp" : 720,
	"loot" : "None",
	"equipped" : [
		"abil_chill",
		"abil_ice",
		"abil_tremble",
		"abil_oice",
		"abil_opara"
	],
	"stats" : {
		"hp" : 202,
		"mhp" : 202,
		"str" : 18,
		"def" : 18,
		"agi" : 26,
		"mana" : 27,
		"flags" : [ ]
	}
}